terminal_ai/__init__.py
terminal_ai/terminal.py
terminal_ai/config/__init__.py
terminal_ai/config/config.py
terminal_ai/constants/__init__.py
terminal_ai/constants/constants.py
terminal_ai/constants/prompts.py
terminal_ai/model/__init__.py
terminal_ai/model/inference.py
terminal_ai/utils/__init__.py
terminal_ai/utils/command_utils.py
terminal_ai/utils/utils.py
ai_terminator-1.0.4.dist-info/METADATA
ai_terminator-1.0.4.dist-info/WHEEL
ai_terminator-1.0.4.dist-info/entry_points.txt
ai_terminator-1.0.4.dist-info/top_level.txt
ai_terminator-1.0.4.dist-info/RECORD
