Metadata-Version: 2.2
Name: ai-terminator
Version: 1.0.4
Summary: A terminal AI assistant that can execute system commands and provide general information.
Author: Himanshu sanecha
Author-email: himanshusanecha@gmail.com
Classifier: Programming Language :: Python :: 3
Classifier: License :: OSI Approved :: MIT License
Classifier: Operating System :: OS Independent
Requires-Python: >=3.6
Requires-Dist: ollama
Requires-Dist: colorama
Requires-Dist: gnureadline
Dynamic: author
Dynamic: author-email
Dynamic: classifier
Dynamic: requires-dist
Dynamic: requires-python
Dynamic: summary
